mediadex/__init__.py
mediadex/exc.py
mediadex/item.py
mediadex/purger.py
mediadex/cmd/__init__.py
mediadex/cmd/app.py
mediadex/cmd/fileinfo.py
mediadex/indexer/__init__.py
mediadex/indexer/movie.py
mediadex/indexer/song.py
mediadex-0.3.2.dist-info/AUTHORS
mediadex-0.3.2.dist-info/METADATA
mediadex-0.3.2.dist-info/WHEEL
mediadex-0.3.2.dist-info/entry_points.txt
mediadex-0.3.2.dist-info/pbr.json
mediadex-0.3.2.dist-info/top_level.txt
mediadex-0.3.2.dist-info/RECORD
